schelp/__init__.py
schelp/__main__.py
schelp/_version.py
schelp/bin.py
schelp/grammar.py
schelp-2023.7.13.2.39.dist-info/METADATA
schelp-2023.7.13.2.39.dist-info/WHEEL
schelp-2023.7.13.2.39.dist-info/top_level.txt
schelp-2023.7.13.2.39.dist-info/RECORD
