Metadata-Version: 2.1
Name: schelp
Version: 2023.7.13.2.39
Summary: Shell helper utilities for python
Home-page: https://github.com/elo-enterprises/schelp/
Author: elo
License: MIT
Project-URL: Documentation, https://github.com/elo-enterprises/schelp/
Project-URL: Source, https://github.com/elo-enterprises/schelp/
Project-URL: Download, https://github.com/elo-enterprises/schelp/#files
Platform: any
Classifier: Programming Language :: Python
Requires-Python: >3.7
Requires-Dist: fleks (==2023.7.13.2.21)
Requires-Dist: TatSu (==5.8.3)
Provides-Extra: dev
Requires-Dist: IPython ; extra == 'dev'
Provides-Extra: lint
Requires-Dist: tox ; extra == 'lint'
Provides-Extra: publish
Requires-Dist: twine ; extra == 'publish'
Provides-Extra: testing
Requires-Dist: IPython ; extra == 'testing'
Requires-Dist: tox ; extra == 'testing'
Requires-Dist: pytest ; extra == 'testing'
Requires-Dist: pytest-cov ; extra == 'testing'
Requires-Dist: mock ; extra == 'testing'
Requires-Dist: flake8 (==5.0.4) ; extra == 'testing'
